bh_aws_wrap/__init__.py
bh_aws_wrap/invoking.py
bh_aws_wrap/test_invoking.py
bh_aws_wrap/test_wrapping_root.py
bh_aws_wrap/test_wrapping_wrap4cmd.py
bh_aws_wrap/tools.py
bh_aws_wrap/util.py
bh_aws_wrap/wrapping.py
bh_aws_wrap/aws/__init__.py
bh_aws_wrap/aws/ec2/__init__.py
bh_aws_wrap/aws/ec2/create_key_pair.py
bh_aws_wrap/aws/ec2/delete_key_pair.py
bh_aws_wrap/aws/ec2/describe_instances.py
bh_aws_wrap/aws/ec2/describe_key_pairs.py
bh_aws_wrap/aws/ec2/hide/DUMMY.py
bh_aws_wrap/aws/ec2/hide/hide_test_describe_instances.py
bh_aws_wrap/aws/ec2/tests/__init__.py
bh_aws_wrap/aws/ec2/tests/test_describe_instances.py
bh_aws_wrap/aws/ec2/tests/test_describe_key_pairs.py
bh_aws_wrap/aws/ec2/tests/conf/__init__.py
bh_aws_wrap-0.0.2b0.dist-info/METADATA
bh_aws_wrap-0.0.2b0.dist-info/WHEEL
bh_aws_wrap-0.0.2b0.dist-info/top_level.txt
bh_aws_wrap-0.0.2b0.dist-info/RECORD
