Metadata-Version: 2.1
Name: bh-aws-wrap
Version: 0.0.2b0
Summary: Add your description here
Requires-Python: >=3.12
Requires-Dist: bh-bump >=0.0.3b0
